odoo/addons/mrp_workorder_lock_planning/README.rst
odoo/addons/mrp_workorder_lock_planning/__init__.py
odoo/addons/mrp_workorder_lock_planning/__manifest__.py
odoo/addons/mrp_workorder_lock_planning/i18n/it.po
odoo/addons/mrp_workorder_lock_planning/i18n/mrp_workorder_lock_planning.pot
odoo/addons/mrp_workorder_lock_planning/models/__init__.py
odoo/addons/mrp_workorder_lock_planning/models/mrp_workorder.py
odoo/addons/mrp_workorder_lock_planning/readme/CONTRIBUTORS.rst
odoo/addons/mrp_workorder_lock_planning/readme/DESCRIPTION.rst
odoo/addons/mrp_workorder_lock_planning/static/description/icon.png
odoo/addons/mrp_workorder_lock_planning/static/description/index.html
odoo/addons/mrp_workorder_lock_planning/tests/__init__.py
odoo/addons/mrp_workorder_lock_planning/tests/test_mrp_workorder_lock_date_planned.py
odoo/addons/mrp_workorder_lock_planning/views/mrp_workorder.xml
odoo_addon_mrp_workorder_lock_planning-15.0.1.0.0.4.dist-info/METADATA
odoo_addon_mrp_workorder_lock_planning-15.0.1.0.0.4.dist-info/WHEEL
odoo_addon_mrp_workorder_lock_planning-15.0.1.0.0.4.dist-info/top_level.txt
odoo_addon_mrp_workorder_lock_planning-15.0.1.0.0.4.dist-info/RECORD
